setup.py
mealy_machine/__init__.py
mealy_machine/mealy_main.py
mealy_machine/mealy_test.py
mealy_machine.egg-info/PKG-INFO
mealy_machine.egg-info/SOURCES.txt
mealy_machine.egg-info/dependency_links.txt
mealy_machine.egg-info/not-zip-safe
mealy_machine.egg-info/top_level.txt