Metadata-Version: 2.1
Name: mealy-machine
Version: 1.0.0
Summary: Mealy machine implementation package
Author-email: andrey.bondar.2003@mail.ru
